{
    "id": "fidwell.scenery_group.ggarden_dkso",
    "authors": ["fidwell"],
    "version": "1.0",
    "originalId": "00000000|TABGIGAR|00000000",
    "sourceGame": "custom",
    "objectType": "scenery_group",
    "properties": {
        "entries": [
            "rct2.scenery_small.ggrs1",
            "$DAT:0C58B301|ETHCLR19",
            "rct2.scenery_small.carrot",
            "$DAT:0C58B301|IRCARROC",
            "rct2.scenery_small.fern1",
            "$DAT:09F55701|MG-RCT73",
            "rct2.scenery_small.spider1",
            "rct2.scenery_small.beanst1",
            "$DAT:00000002|GWTRGBS1",
            "rct2.scenery_small.beanst2",
            "$DAT:00000002|GWTRGBS2",
            "rct2.scenery_small.buttfly",
            "rct2.scenery_small.snail",
            "rct2.scenery_small.wasp",
            "rct2.footpath_item.lampdsy"
        ],
        "priority": 35
    },
    "images": [
        {
            "path": "images\/0.png"
        },
        {
            "path": "images\/1.png"
        }
    ],
    "strings": {
        "name": {
            "en-GB": "DKSO Giant Garden Theming",
            "fr-FR": "DKSO Thème Jardin géant",
            "de-DE": "DKSO Riesengarten-Thema",
            "es-ES": "DKSO Temática jardín gigante",
            "it-IT": "DKSO Tema giardino gigante",
            "nl-NL": "DKSO Gigantische-tuin-thema",
            "sv-SE": "DKSO Gigantisk trädgård-tema",
            "ko-KR": "DKSO 대형 정원 테마",
            "zh-CN": "DKSO 巨大花园主题",
            "zh-TW": "DKSO 巨大花園主題區",
            "pt-BR": "DKSO Temática de Jardim Gigante",
            "cs-CZ": "DKSO Kulisy obrovských zahrad",
            "ja-JP": "DKSO 巨大花壇風のテーマ",
            "pl-PL": "DKSO Wystrój ogrodu olbrzymów",
            "ru-RU": "DKSO Гигантский Сад",
            "eo-ZZ": "DKSO Temo de Giganta Ĝardeno",
            "ca-ES": "DKSO Temàtica de jardí gegant",
            "fi-FI": "DKSO Jättipuutarhateemaus"
        }
    }
}
