{
    "id": "fidwell.v3.scenery_group.space_dkso",
    "authors": ["fidwell"],
    "version": "1.0",
    "sourceGame": "custom",
    "objectType": "scenery_group",
    "properties": {
        "entries": [
            "rct2.scenery_large.ssr",
            "rct2.scenery_large.sst",
            "rct2.scenery_large.ssh",
            "rct2.scenery_small.tscp",
            "rct2.scenery_small.tsph",
            "fidwell.v1.scenery_small.tsph",
            "rct2.scenery_small.tsc2",
            "rct2.scenery_small.tsp1",
            "fidwell.v2.scenery_small.tsp1",
            "rct2.scenery_small.tsp2",
            "rct2.scenery_wall.wallsp32",
            "fidwell.v1.scenery_wall.wallsp32",
            "rct2.scenery_small.spcroof1",
            "fidwell.v1.scenery_small.spcroof1",
            "rct2.footpath_banner.bn9",
            "rct2.footpath_item.benchspc",
            "rct2.footpath_item.littersp"
        ],
        "priority": 31
    },
    "images": [
        {
            "path": "images\/0.png"
        },
        {
            "path": "images\/1.png"
        }
    ],
    "strings": {
        "name": {
            "en-GB": "DKSO v3 Space Theming",
            "fr-FR": "DKSO v3 Thème Espace",
            "de-DE": "DKSO v3 Weltraumthema",
            "es-ES": "DKSO v3 Temática espacial",
            "it-IT": "DKSO v3 Tema spaziale",
            "nl-NL": "DKSO v3 Ruimtethema",
            "sv-SE": "DKSO v3 Rymdtema",
            "ko-KR": "DKSO v3 우주 테마",
            "zh-CN": "DKSO v3 太空世界主题",
            "zh-TW": "DKSO v3 太空世界主題區",
            "pt-BR": "DKSO v3 Temática Espacial",
            "cs-CZ": "DKSO v3 Vesmírné kulisy",
            "ja-JP": "DKSO v3 スペース風のテーマ",
            "pl-PL": "DKSO v3 Wystrój kosmiczny",
            "ru-RU": "DKSO v3 Космос",
            "eo-ZZ": "DKSO v3 Kosma Temo",
            "ca-ES": "DKSO v3 Temàtica espacial",
            "fi-FI": "DKSO v3 Avaruusteemaus"
        }
    }
}
